repository_service_tuf/__init__.py
repository_service_tuf/__version__.py
repository_service_tuf/cli/__init__.py
repository_service_tuf/cli/admin/__init__.py
repository_service_tuf/cli/admin/ceremony.py
repository_service_tuf/cli/admin/helpers.py
repository_service_tuf/cli/admin/import_artifacts.py
repository_service_tuf/cli/admin/delegations/__init__.py
repository_service_tuf/cli/admin/delegations/delete.py
repository_service_tuf/cli/admin/delegations/new.py
repository_service_tuf/cli/admin/metadata/__init__.py
repository_service_tuf/cli/admin/metadata/sign.py
repository_service_tuf/cli/admin/metadata/stop_sign.py
repository_service_tuf/cli/admin/metadata/update.py
repository_service_tuf/cli/admin/send/__init__.py
repository_service_tuf/cli/admin/send/bootstrap.py
repository_service_tuf/cli/admin/send/sign.py
repository_service_tuf/cli/admin/send/update.py
repository_service_tuf/cli/artifact/__init__.py
repository_service_tuf/cli/artifact/add.py
repository_service_tuf/cli/artifact/delete.py
repository_service_tuf/cli/artifact/download.py
repository_service_tuf/cli/artifact/repository.py
repository_service_tuf/cli/task/__init__.py
repository_service_tuf/cli/task/info.py
repository_service_tuf/helpers/__init__.py
repository_service_tuf/helpers/api_client.py
repository_service_tuf/helpers/cli.py
repository_service_tuf-1.0.0b1.dist-info/METADATA
repository_service_tuf-1.0.0b1.dist-info/WHEEL
repository_service_tuf-1.0.0b1.dist-info/entry_points.txt
repository_service_tuf-1.0.0b1.dist-info/licenses/LICENSE
repository_service_tuf-1.0.0b1.dist-info/RECORD
