Metadata-Version: 2.4
Name: repository-service-tuf
Version: 1.0.0b1
Summary: Repository Service for TUF Command Line Interface
Author-email: Kairo de Araujo <kairo@dearaujo.nl>
License: MIT
License-File: LICENSE
Classifier: Development Status :: 4 - Beta
Classifier: Programming Language :: Python
Classifier: Programming Language :: Python :: 3.10
Classifier: Programming Language :: Python :: 3.11
Classifier: Programming Language :: Python :: 3.12
Classifier: Programming Language :: Python :: 3.13
Classifier: Programming Language :: Python :: Implementation :: CPython
Classifier: Programming Language :: Python :: Implementation :: PyPy
Requires-Python: >=3.10
Requires-Dist: asn1crypto
Requires-Dist: auto-click-auto
Requires-Dist: azure-keyvault-keys
Requires-Dist: beaupy
Requires-Dist: boto3
Requires-Dist: click
Requires-Dist: dynaconf[ini]
Requires-Dist: google-cloud-kms
Requires-Dist: hvac
Requires-Dist: prompt-toolkit
Requires-Dist: pykcs11
Requires-Dist: pynacl
Requires-Dist: requests
Requires-Dist: rich
Requires-Dist: rich-click
Requires-Dist: securesystemslib[crypto]
Requires-Dist: setuptools
Requires-Dist: sigstore
Requires-Dist: tuf
Provides-Extra: psycopg2
Requires-Dist: psycopg2>=2.9.5; extra == 'psycopg2'
Provides-Extra: sqlalchemy
Requires-Dist: sqlalchemy>=2.0.1; extra == 'sqlalchemy'
